flask_xtra_info/__init__.py
flask_xtra_info-0.3.15.dist-info/LICENSE
flask_xtra_info-0.3.15.dist-info/METADATA
flask_xtra_info-0.3.15.dist-info/WHEEL
flask_xtra_info-0.3.15.dist-info/top_level.txt
flask_xtra_info-0.3.15.dist-info/RECORD
