Metadata-Version: 2.1
Name: flask-xtra-info
Version: 0.3.15
Summary: Inject extra info into flask headers and logs.
License: MIT
Keywords: request_id,header
Classifier: Development Status :: 5 - Production/Stable
Classifier: Environment :: Web Environment
Classifier: Framework :: Flask
Classifier: License :: OSI Approved :: MIT License
License-File: LICENSE
Requires-Dist: flask
Requires-Dist: importlib-metadata ; python_version < "3.8"
